{"author":"bluemeany","questions":[{"type":"quiz","question":"All <b>robots </b>look like human beings...","time":20000,"points":true,"pointsMultiplier":1,"choices":[{"answer":"True","correct":false},{"answer":"False","correct":true}],"image":"https://media.kahoot.it/3877b8b6-421d-47f8-82ea-5ac6eb9a7929_opt","imageMetadata":{"id":"3877b8b6-421d-47f8-82ea-5ac6eb9a7929","resources":""},"resources":"","video":{"id":"","startTime":0,"endTime":0,"service":"youtube","fullUrl":""},"questionFormat":0},{"type":"quiz","question":"\"<b>Robot</b>\" is a Czech word that means 'creator'...","time":20000,"points":true,"pointsMultiplier":1,"choices":[{"answer":"True","correct":false},{"answer":"False","correct":true}],"image":"https://media.kahoot.it/bc1fe958-156e-4c1c-a08c-d2b31a002209_opt","imageMetadata":{"id":"bc1fe958-156e-4c1c-a08c-d2b31a002209","resources":""},"resources":"","video":{"id":"","startTime":0,"endTime":0,"service":"youtube","fullUrl":""},"questionFormat":0},{"type":"quiz","question":"<b>Robots </b>are usually ______ devices that move in every direction using sophisticated electronics","time":20000,"points":true,"pointsMultiplier":1,"choices":[{"answer":"Cam driven","correct":false},{"answer":"Eccentric","correct":false},{"answer":"Mechanical","correct":true},{"answer":"Exciting","correct":false}],"image":"https://media.kahoot.it/68bd071f-590e-4e32-a90f-922cf33b9c84_opt","imageMetadata":{"id":"68bd071f-590e-4e32-a90f-922cf33b9c84","resources":""},"resources":"","video":{"id":"","startTime":0,"endTime":0,"service":"youtube","fullUrl":""},"questionFormat":0},{"type":"quiz","question":"Examples of where <b>robots </b>are used include exploration, assembly and __________","time":20000,"points":true,"pointsMultiplier":1,"choices":[{"answer":"Observation","correct":false},{"answer":"Inclusion","correct":false},{"answer":"Designing","correct":false},{"answer":"Packaging and dispatch","correct":true}],"image":"https://media.kahoot.it/5a8227f0-8f95-424a-8d59-403201186912_opt","imageMetadata":{"id":"5a8227f0-8f95-424a-8d59-403201186912","resources":""},"resources":"","video":{"id":"","startTime":0,"endTime":0,"service":"youtube","fullUrl":""},"questionFormat":0},{"type":"quiz","question":"<b>ROV </b>stands for..?","time":20000,"points":true,"pointsMultiplier":1,"choices":[{"answer":"Remote Operated Vehicles","correct":true},{"answer":"Remote Operated Venticle","correct":false},{"answer":"Replicate Operated Vehicles","correct":false},{"answer":"Remote Observatory Vehicles","correct":false}],"image":"https://media.kahoot.it/c2f93145-ab7e-41f6-aa8a-0a6426988021_opt","imageMetadata":{"id":"c2f93145-ab7e-41f6-aa8a-0a6426988021","resources":""},"resources":"","video":{"id":"","startTime":0,"endTime":0,"service":"youtube","fullUrl":""},"questionFormat":0},{"type":"quiz","question":"<b>Remote operated vehicles </b>(ROV) can be used for searching for lost ships in the ocean and..?","time":20000,"points":true,"pointsMultiplier":1,"choices":[{"answer":"Sport","correct":false},{"answer":"Space exploration","correct":true},{"answer":"Entertainment","correct":false}],"image":"https://media.kahoot.it/3ec7c865-6ba4-4b8a-8c30-0011d6af166a_opt","imageMetadata":{"id":"3ec7c865-6ba4-4b8a-8c30-0011d6af166a","resources":""},"resources":"","video":{"id":"","startTime":0,"endTime":0,"service":"youtube","fullUrl":""},"questionFormat":0},{"type":"quiz","question":"<b>Robots </b>can work in places that are dangerous to human beings..?","time":20000,"points":true,"pointsMultiplier":1,"choices":[{"answer":"True","correct":true},{"answer":"False","correct":false}],"image":"https://media.kahoot.it/2f37e1ef-2908-4575-9be9-d89356dfd703_opt","imageMetadata":{"id":"2f37e1ef-2908-4575-9be9-d89356dfd703","resources":""},"resources":"","video":{"id":"","startTime":0,"endTime":0,"service":"youtube","fullUrl":""},"questionFormat":0},{"type":"quiz","question":"CNC stands for...?","time":20000,"points":true,"pointsMultiplier":1,"choices":[{"answer":"Computer Numerically Created","correct":false},{"answer":"Conductive Numerically Controlled","correct":false},{"answer":"Creative Numerically Controlled","correct":false},{"answer":"Computer Numerically Controlled","correct":true}],"image":"https://media.kahoot.it/3b1680fd-4c3f-45a1-bea6-b25d9408e141_opt","imageMetadata":{"id":"3b1680fd-4c3f-45a1-bea6-b25d9408e141","resources":""},"resources":"","video":{"id":"","startTime":0,"endTime":0,"service":"youtube","fullUrl":""},"questionFormat":0},{"type":"quiz","question":"A CNC milling machine is controlled by an operator (human being) by hand?","time":20000,"points":true,"pointsMultiplier":1,"choices":[{"answer":"True","correct":false},{"answer":"False","correct":true}],"image":"https://media.kahoot.it/ee1f0897-2ed6-400b-86ab-a650e37bfe03_opt","imageMetadata":{"id":"ee1f0897-2ed6-400b-86ab-a650e37bfe03","resources":""},"resources":"","video":{"id":"","startTime":0,"endTime":0,"service":"youtube","fullUrl":""},"questionFormat":0},{"type":"quiz","question":"A CNC machine is controlled by a computer. The computer has the ability to control..?","time":20000,"points":true,"pointsMultiplier":1,"choices":[{"answer":"The spindle","correct":false},{"answer":"The movement of the table","correct":false},{"answer":"The spindle and the movement of the table","correct":true}],"image":"https://media.kahoot.it/a8eb4112-8429-4063-a861-7cb069702f49_opt","imageMetadata":{"id":"a8eb4112-8429-4063-a861-7cb069702f49","resources":""},"resources":"","video":{"id":"","startTime":0,"endTime":0,"service":"youtube","fullUrl":""},"questionFormat":0},{"type":"quiz","question":"The CNC machine is mainly used to create ___ shapes","time":20000,"points":true,"pointsMultiplier":1,"choices":[{"answer":"2D","correct":false},{"answer":"3D","correct":true},{"answer":"4D","correct":false},{"answer":"5D","correct":false}],"image":"https://media.kahoot.it/cf81a7b4-24f6-4317-9151-2170cde41208_opt","imageMetadata":{"id":"cf81a7b4-24f6-4317-9151-2170cde41208","resources":""},"resources":"","video":{"id":"","startTime":0,"endTime":0,"service":"youtube","fullUrl":""},"questionFormat":0},{"type":"quiz","question":"Some CNC machines are so clever they can detect wear on the cutting tool &amp; adapt where it cuts","time":20000,"points":true,"pointsMultiplier":1,"choices":[{"answer":"True","correct":true},{"answer":"False","correct":false}],"image":"https://media.kahoot.it/ad59c36b-7444-45d6-abe9-a006e48db0a6_opt","imageMetadata":{"id":"ad59c36b-7444-45d6-abe9-a006e48db0a6","resources":""},"resources":"","video":{"id":"","startTime":0,"endTime":0,"service":"youtube","fullUrl":""},"questionFormat":0},{"type":"quiz","question":"Some CNC machines can adjust themselves or change the tool without stopping","time":20000,"points":true,"pointsMultiplier":1,"choices":[{"answer":"True","correct":true},{"answer":"False","correct":false}],"image":"https://media.kahoot.it/ba55f5d9-1026-485e-9555-978bb686e7e9_opt","imageMetadata":{"id":"ba55f5d9-1026-485e-9555-978bb686e7e9","resources":""},"resources":"","video":{"id":"","startTime":0,"endTime":0,"service":"youtube","fullUrl":""},"questionFormat":0},{"type":"quiz","question":"Today, CNC machining is often referred to as...?","time":20000,"points":true,"pointsMultiplier":1,"choices":[{"answer":"CAD","correct":false},{"answer":"CAM","correct":true},{"answer":"CIM","correct":false},{"answer":"CEM","correct":false}],"image":"https://media.kahoot.it/9b8b8fb4-54fb-4d15-99fc-39f9dbeca27a_opt","imageMetadata":{"id":"9b8b8fb4-54fb-4d15-99fc-39f9dbeca27a","resources":""},"resources":"","video":{"id":"","startTime":0,"endTime":0,"service":"youtube","fullUrl":""},"questionFormat":0},{"type":"quiz","question":"CAM stands for..?","time":20000,"points":true,"pointsMultiplier":1,"choices":[{"answer":"Constructive Aided Manufacturing","correct":false},{"answer":"Computer Aided Manufacturing","correct":true},{"answer":"Controlled Aided Manufacturing","correct":false},{"answer":"Computer Axis Manufacturing","correct":false}],"image":"https://media.kahoot.it/fbdbc474-192b-48b8-81ae-f5082e28f12f_opt","imageMetadata":{"id":"fbdbc474-192b-48b8-81ae-f5082e28f12f","resources":""},"resources":"","video":{"id":"","startTime":0,"endTime":0,"service":"youtube","fullUrl":""},"questionFormat":0},{"type":"quiz","question":"CAM usually relies on the use of..?","time":20000,"points":true,"pointsMultiplier":1,"choices":[{"answer":"CID","correct":false},{"answer":"CUD","correct":false},{"answer":"CED","correct":false},{"answer":"CAD","correct":true}],"image":"https://media.kahoot.it/18efe630-55d5-47e2-96a7-6762d83eaf13_opt","imageMetadata":{"id":"18efe630-55d5-47e2-96a7-6762d83eaf13","resources":""},"resources":"","video":{"id":"","startTime":0,"endTime":0,"service":"youtube","fullUrl":""},"questionFormat":0},{"type":"quiz","question":"CAD stands for..?","time":20000,"points":true,"pointsMultiplier":1,"choices":[{"answer":"Computer Aided Design","correct":true},{"answer":"Computer Aided Definition","correct":false},{"answer":"Computer Aided Diagrams","correct":false},{"answer":"Computer Aided Demographics","correct":false}],"image":"https://media.kahoot.it/7f8e6fe2-dd83-4417-b068-c6d54a13349b_opt","imageMetadata":{"id":"7f8e6fe2-dd83-4417-b068-c6d54a13349b","resources":""},"resources":"","video":{"id":"","startTime":0,"endTime":0,"service":"youtube","fullUrl":""},"questionFormat":0},{"type":"quiz","question":"An advantage of using CAD/CAM and CNC machinery is that it is..?","time":20000,"points":true,"pointsMultiplier":1,"choices":[{"answer":"Very accurate","correct":true},{"answer":"Very slow","correct":false},{"answer":"Very quick","correct":true},{"answer":"Very cheap","correct":false}],"image":"https://media.kahoot.it/92f536e2-859d-4336-b283-0f2320cedfcd_opt","imageMetadata":{"id":"92f536e2-859d-4336-b283-0f2320cedfcd","resources":""},"resources":"","video":{"id":"","startTime":0,"endTime":0,"service":"youtube","fullUrl":""},"questionFormat":0},{"type":"quiz","question":"A disadvantage of CAD/CAM and CNC machinery is that it..?","time":20000,"points":true,"pointsMultiplier":1,"choices":[{"answer":"Requires specialist training","correct":true},{"answer":"Needs a high initial investment","correct":true},{"answer":"Workers can lose skills due to relying on CAD/CAM","correct":true},{"answer":"Can raise unemployment","correct":true}],"image":"https://media.kahoot.it/d0f84880-acec-4518-966e-1e60da6e3228_opt","imageMetadata":{"id":"d0f84880-acec-4518-966e-1e60da6e3228","resources":""},"resources":"","video":{"id":"","startTime":0,"endTime":0,"service":"youtube","fullUrl":""},"questionFormat":0}],"answerMap":[2,2,4,4,4,3,2,4,2,3,4,2,2,4,4,4,4,4,4],"uuid":"162eebe2-883b-4046-96c4-06a219ab80cf"}