{"author":"JadenMcGrath","questions":[{"type":"quiz","question":"Who is the first member of the boarding school Clementine met?","time":20000,"points":true,"pointsMultiplier":1,"choices":[{"answer":"Louis","correct":false},{"answer":"Marlon","correct":false},{"answer":"Tenn","correct":true},{"answer":"Violet","correct":false}],"image":"https://media.kahoot.it/9930746b-7ba9-42e3-95be-69ac610ca64d_opt","imageMetadata":{"id":"9930746b-7ba9-42e3-95be-69ac610ca64d","resources":""},"resources":"","video":{"id":"","startTime":0,"endTime":0,"service":"youtube","fullUrl":""},"questionFormat":0},{"type":"quiz","question":"What is the name of Lilly's camp?","time":20000,"points":true,"pointsMultiplier":1,"choices":[{"answer":"The Delta","correct":true},{"answer":"The Stronghold","correct":false},{"answer":"The Haven","correct":false},{"answer":"The Core","correct":false}],"image":"https://media.kahoot.it/4c6217f4-02d2-434b-91af-eef3a964c639_opt","imageMetadata":{"id":"4c6217f4-02d2-434b-91af-eef3a964c639","resources":""},"resources":"","video":{"id":"","startTime":0,"endTime":0,"service":"youtube","fullUrl":""},"questionFormat":0},{"type":"quiz","question":"Which of the follow people does Clementine NOT have the option of saying she has feelings for?","time":20000,"points":true,"pointsMultiplier":1,"choices":[{"answer":"Louis","correct":false},{"answer":"James","correct":true},{"answer":"Gabe","correct":false},{"answer":"Violet","correct":false}],"image":"https://media.kahoot.it/6f21c276-fac0-4eca-b0cf-502cd97215ed_opt","imageMetadata":{"id":"6f21c276-fac0-4eca-b0cf-502cd97215ed","resources":""},"resources":"","video":{"id":"","startTime":0,"endTime":0,"service":"youtube","fullUrl":""},"questionFormat":0},{"type":"quiz","question":"Which of the following people did Lilly and her people end up not kidnapping?","time":20000,"points":true,"pointsMultiplier":1,"choices":[{"answer":"Mitch","correct":true},{"answer":"Omar","correct":false},{"answer":"Louis/Violet","correct":false},{"answer":"Aasim","correct":false}],"image":"https://media.kahoot.it/f4b2f0e1-62d0-478b-9858-e7f4da7a5d42_opt","imageMetadata":{"id":"f4b2f0e1-62d0-478b-9858-e7f4da7a5d42","resources":""},"resources":"","video":{"id":"","startTime":0,"endTime":0,"service":"youtube","fullUrl":""},"questionFormat":0},{"type":"quiz","question":"What are the names of Tenn's twin sisters?","time":20000,"points":true,"pointsMultiplier":1,"choices":[{"answer":"Violet and Brody","correct":false},{"answer":"Sasha and Kate","correct":false},{"answer":"Sophie and Minerva","correct":true},{"answer":"Lilly and Christa","correct":false}],"image":"https://media.kahoot.it/53e6fb46-4d75-4238-a15f-975f8a9b081c","imageMetadata":{"id":"53e6fb46-4d75-4238-a15f-975f8a9b081c","resources":""},"resources":"","video":{"id":"","startTime":0,"endTime":0,"service":"youtube","fullUrl":""},"questionFormat":0},{"type":"quiz","question":"What was the reason why Mitch was sent to the boarding school before the apocalypse?","time":20000,"points":true,"pointsMultiplier":1,"choices":[{"answer":"He fought another kid.","correct":false},{"answer":"He murdered his pet cat.","correct":false},{"answer":"He set off a bomb in his garage.","correct":true},{"answer":"He knocked out a teacher.","correct":false}],"image":"https://media.kahoot.it/2151c1f8-4198-4c4f-9750-e20136ea9ea7_opt","imageMetadata":{"id":"2151c1f8-4198-4c4f-9750-e20136ea9ea7","resources":""},"resources":"","video":{"id":"","startTime":0,"endTime":0,"service":"youtube","fullUrl":""},"questionFormat":0},{"type":"quiz","question":"Which of the following toys were not included in the game?","time":20000,"points":true,"pointsMultiplier":1,"choices":[{"answer":"A Robot Soldier","correct":true},{"answer":"A Fireman","correct":false},{"answer":"A Policeman","correct":false},{"answer":"A Disco Broccoli","correct":false}],"image":"https://media.kahoot.it/40c33f32-afd2-4b76-9384-c9eca7668505_opt","imageMetadata":{"id":"40c33f32-afd2-4b76-9384-c9eca7668505","resources":""},"resources":"","video":{"id":"","startTime":0,"endTime":0,"service":"youtube","fullUrl":""},"questionFormat":0},{"type":"quiz","question":"Upon falling of the balcony during the attack on the school, Abel ends up breaking what?","time":20000,"points":true,"pointsMultiplier":1,"choices":[{"answer":"Clem's Hand","correct":false},{"answer":"His Foot","correct":false},{"answer":"His Arm","correct":false},{"answer":"His Leg","correct":true}],"image":"https://media.kahoot.it/0f4247b2-c913-4bdf-9c35-583c524e7791_opt","imageMetadata":{"id":"0f4247b2-c913-4bdf-9c35-583c524e7791","resources":""},"resources":"","video":{"id":"","startTime":0,"endTime":0,"service":"youtube","fullUrl":""},"questionFormat":0},{"type":"quiz","question":"When first arriving at the school, who does AJ accidently bite when getting startled?","time":20000,"points":true,"pointsMultiplier":1,"choices":[{"answer":"Louis","correct":false},{"answer":"Ruby","correct":true},{"answer":"Marlon","correct":false},{"answer":"Willy","correct":false}],"image":"https://media.kahoot.it/cb0c84d6-cae6-4561-97d8-c69bf1ea4c54_opt","imageMetadata":{"id":"cb0c84d6-cae6-4561-97d8-c69bf1ea4c54","resources":""},"resources":"","video":{"id":"","startTime":0,"endTime":0,"service":"youtube","fullUrl":""},"questionFormat":0},{"type":"quiz","question":"During the game of war, Clementine can reference the following people except who?","time":20000,"points":true,"pointsMultiplier":1,"choices":[{"answer":"Javier","correct":false},{"answer":"Mark","correct":false},{"answer":"Carver","correct":false},{"answer":"Luke","correct":true}],"image":"https://media.kahoot.it/0734020d-fe38-45db-bf3f-080539717b87_opt","imageMetadata":{"id":"0734020d-fe38-45db-bf3f-080539717b87","resources":""},"resources":"","video":{"id":"","startTime":0,"endTime":0,"service":"youtube","fullUrl":""},"questionFormat":0},{"type":"quiz","question":"Who looks after AJ while Clem is unconscious?","time":20000,"points":true,"pointsMultiplier":1,"choices":[{"answer":"Violet","correct":false},{"answer":"Marlon","correct":false},{"answer":"Louis","correct":true},{"answer":"Brody","correct":false}],"image":"https://media.kahoot.it/bf27a243-82b5-46fd-b0be-5acd9f8d52b2_opt","imageMetadata":{"id":"bf27a243-82b5-46fd-b0be-5acd9f8d52b2","resources":""},"resources":"","video":{"id":"","startTime":0,"endTime":0,"service":"youtube","fullUrl":""},"questionFormat":0},{"type":"quiz","question":"Mitch said that once the apocalypse started, he got rid of what around the school?","time":20000,"points":true,"pointsMultiplier":1,"choices":[{"answer":"The Books and Pencils","correct":false},{"answer":"The Chalkboards","correct":false},{"answer":"The Old Homework","correct":false},{"answer":"The Inspirational Posters","correct":true}],"image":"https://media.kahoot.it/727fcd85-0752-4a3a-ad80-77e0dd2d0ffd_opt","imageMetadata":{"id":"727fcd85-0752-4a3a-ad80-77e0dd2d0ffd","resources":""},"resources":"","video":{"id":"","startTime":0,"endTime":0,"service":"youtube","fullUrl":""},"questionFormat":0},{"type":"quiz","question":"When Clementine plays Marry Flip Kill, which of the following is not an option?","time":20000,"points":true,"pointsMultiplier":1,"choices":[{"answer":"Aasim","correct":false},{"answer":"Louis","correct":true},{"answer":"James","correct":false},{"answer":"Ruby","correct":false}],"image":"https://media.kahoot.it/e4e117f7-9a1e-4d55-82a2-f2d44ddc1867_opt","imageMetadata":{"id":"e4e117f7-9a1e-4d55-82a2-f2d44ddc1867","resources":""},"resources":"","video":{"id":"","startTime":0,"endTime":0,"service":"youtube","fullUrl":""},"questionFormat":0},{"type":"quiz","question":"What is the reoccurring nightmare that Clementine has about?","time":20000,"points":true,"pointsMultiplier":1,"choices":[{"answer":"New Richmond Being Destroyed","correct":false},{"answer":"The McCarroll Ranch","correct":true},{"answer":"Losing AJ","correct":false},{"answer":"Lee's Death","correct":false}],"image":"https://media.kahoot.it/1c96cb24-6918-4400-81f7-bfb2f3358972_opt","imageMetadata":{"id":"1c96cb24-6918-4400-81f7-bfb2f3358972","resources":""},"resources":"","video":{"id":"","startTime":0,"endTime":0,"service":"youtube","fullUrl":""},"questionFormat":0},{"type":"quiz","question":"Who does Lilly accidently kill during her attack?","time":20000,"points":true,"pointsMultiplier":1,"choices":[{"answer":"Mitch","correct":true},{"answer":"Willy","correct":false},{"answer":"Abel","correct":false},{"answer":"Aasim","correct":false}],"image":"https://media.kahoot.it/360d7815-8f2d-416d-a1fa-4017e82d056c_opt","imageMetadata":{"id":"360d7815-8f2d-416d-a1fa-4017e82d056c","resources":""},"resources":"","video":{"id":"","startTime":0,"endTime":0,"service":"youtube","fullUrl":""},"questionFormat":0},{"type":"quiz","question":"Who is revealed to have a crush on Ruby?","time":20000,"points":true,"pointsMultiplier":1,"choices":[{"answer":"Louis","correct":false},{"answer":"Aasim","correct":true},{"answer":"Mitch","correct":false},{"answer":"Willy","correct":false}],"image":"https://media.kahoot.it/53988e21-8923-42a6-9bb1-a9de641fb40e_opt","imageMetadata":{"id":"53988e21-8923-42a6-9bb1-a9de641fb40e","resources":""},"resources":"","video":{"id":"","startTime":0,"endTime":0,"service":"youtube","fullUrl":""},"questionFormat":0},{"type":"quiz","question":"What instrument does Louis love to play the most?","time":20000,"points":true,"pointsMultiplier":1,"choices":[{"answer":"Accordian","correct":false},{"answer":"Guitar","correct":false},{"answer":"Clarinet","correct":false},{"answer":"Piano","correct":true}],"image":"https://media.kahoot.it/c6a1e52e-cc76-429a-a524-766dcf6c546f_opt","imageMetadata":{"id":"c6a1e52e-cc76-429a-a524-766dcf6c546f","resources":""},"resources":"","video":{"id":"","startTime":0,"endTime":0,"service":"youtube","fullUrl":""},"questionFormat":0},{"type":"quiz","question":"Who trades away Tenn’s sisters in exchange for protection?","time":20000,"points":true,"pointsMultiplier":1,"choices":[{"answer":"Brody","correct":false},{"answer":"Marlon","correct":true},{"answer":"Abel","correct":false},{"answer":"Clementine","correct":false}],"image":"https://media.kahoot.it/5e23f8dd-e0db-46c4-9e2e-ff08364ba16b_opt","imageMetadata":{"id":"5e23f8dd-e0db-46c4-9e2e-ff08364ba16b","resources":""},"resources":"","video":{"id":"","startTime":0,"endTime":0,"service":"youtube","fullUrl":""},"questionFormat":0},{"type":"quiz","question":"What is the first collectible you can pick up in the game?","time":20000,"points":true,"pointsMultiplier":1,"choices":[{"answer":"A Deer’s Skull","correct":true},{"answer":"A Venus Fly Trap","correct":false},{"answer":"Fake Flowers","correct":false},{"answer":"AJ’s Drawing","correct":false}],"image":"https://media.kahoot.it/a955b299-0cd0-4ccb-bf17-c4a2b37e13de_opt","imageMetadata":{"id":"a955b299-0cd0-4ccb-bf17-c4a2b37e13de","resources":""},"resources":"","video":{"id":"","startTime":0,"endTime":0,"service":"youtube","fullUrl":""},"questionFormat":0},{"type":"quiz","question":"When Clementine can optionally carve a heart on Louis’s piano, what does he mistake it for?","time":20000,"points":true,"pointsMultiplier":1,"choices":[{"answer":"A Head","correct":false},{"answer":"A Butt","correct":false},{"answer":"A Potato","correct":true},{"answer":"An Apple","correct":false}],"image":"https://media.kahoot.it/feebd27c-cdbb-4c9b-ab0c-5c1d52dec6db_opt","imageMetadata":{"id":"feebd27c-cdbb-4c9b-ab0c-5c1d52dec6db","resources":""},"resources":"","video":{"id":"","startTime":0,"endTime":0,"service":"youtube","fullUrl":""},"questionFormat":0},{"type":"quiz","question":"During the game of War, what was the first question asked?","time":20000,"points":true,"pointsMultiplier":1,"choices":[{"answer":"If Clem Ever Had A Boyfriend","correct":false},{"answer":"What Happened To AJ’s Parents","correct":true},{"answer":"Who Took Care Of Clem At The Start Of The Apocalypse","correct":false},{"answer":"Who Did Clem Think Would Die First","correct":false}],"image":"https://media.kahoot.it/86f1dc74-e8b1-49c7-a3c1-3fbe3c758946_opt","imageMetadata":{"id":"86f1dc74-e8b1-49c7-a3c1-3fbe3c758946","resources":""},"resources":"","video":{"id":"","startTime":0,"endTime":0,"service":"youtube","fullUrl":""},"questionFormat":0},{"type":"quiz","question":"What was the name of the nurse of the boarding school who turned into a walker?","time":20000,"points":true,"pointsMultiplier":1,"choices":[{"answer":"Mrs. Martin","correct":true},{"answer":"Mrs. Turner","correct":false},{"answer":"Mrs. Peregrine","correct":false},{"answer":"Mrs. Garth","correct":false}],"image":"https://media.kahoot.it/549652e6-a84b-4349-8a71-322f9383acac_opt","imageMetadata":{"id":"549652e6-a84b-4349-8a71-322f9383acac","resources":""},"resources":"","video":{"id":"","startTime":0,"endTime":0,"service":"youtube","fullUrl":""},"questionFormat":0},{"type":"quiz","question":"Who ends up killing Marlon after he surrenders?","time":20000,"points":true,"pointsMultiplier":1,"choices":[{"answer":"Clementine","correct":false},{"answer":"Louis","correct":false},{"answer":"AJ","correct":true},{"answer":"He Kills Himself","correct":false}],"image":"https://media.kahoot.it/461e8f22-9ee6-4fbe-8c64-b9926cc9030d_opt","imageMetadata":{"id":"461e8f22-9ee6-4fbe-8c64-b9926cc9030d","resources":""},"resources":"","video":{"id":"","startTime":0,"endTime":0,"service":"youtube","fullUrl":""},"questionFormat":0},{"type":"quiz","question":"Who gets upset when Clementine talks about meeting Abel?","time":20000,"points":true,"pointsMultiplier":1,"choices":[{"answer":"Marlon","correct":false},{"answer":"Tenn","correct":false},{"answer":"Aasim","correct":false},{"answer":"Brody","correct":true}],"image":"https://media.kahoot.it/5b85a4e7-5d84-4f09-983d-23667c321d8f_opt","imageMetadata":{"id":"5b85a4e7-5d84-4f09-983d-23667c321d8f","resources":""},"resources":"","video":{"id":"","startTime":0,"endTime":0,"service":"youtube","fullUrl":""},"questionFormat":0},{"type":"quiz","question":"When the raiders attack the school, there is a banner hanging from it that says what?","time":20000,"points":true,"pointsMultiplier":1,"choices":[{"answer":"“Get The Hell Out”","correct":false},{"answer":"“You Don’t Belong Here”","correct":false},{"answer":"“Leave Or Die”","correct":true},{"answer":"“We‘ll Never Be Yours”","correct":false}],"image":"https://media.kahoot.it/47969371-5b67-4d75-847b-42efc4d51a89_opt","imageMetadata":{"id":"47969371-5b67-4d75-847b-42efc4d51a89","resources":""},"resources":"","video":{"id":"","startTime":0,"endTime":0,"service":"youtube","fullUrl":""},"questionFormat":0},{"type":"quiz","question":"So far, what game have none of the kids played?","time":20000,"points":true,"pointsMultiplier":1,"choices":[{"answer":"War","correct":false},{"answer":"Euchre","correct":true},{"answer":"Rock Paper Scissors","correct":false},{"answer":"Truth Or Dare","correct":false}],"image":"https://media.kahoot.it/90cf8ced-92e8-4203-b30c-64c937c4fcce_opt","imageMetadata":{"id":"90cf8ced-92e8-4203-b30c-64c937c4fcce","resources":""},"resources":"","video":{"id":"","startTime":0,"endTime":0,"service":"youtube","fullUrl":""},"questionFormat":0},{"type":"quiz","question":"What does Violet say in response to Clementine’s optional kiss?","time":20000,"points":true,"pointsMultiplier":1,"choices":[{"answer":"“Wow.”","correct":false},{"answer":"“Hell yeah.”","correct":false},{"answer":"“About Damn Time.”","correct":false},{"answer":"“Holy Shit”","correct":true}],"image":"https://media.kahoot.it/4d13e2be-1c4a-45e7-bde7-5608da7ff815","imageMetadata":{"id":"4d13e2be-1c4a-45e7-bde7-5608da7ff815","resources":""},"resources":"","video":{"id":"","startTime":0,"endTime":0,"service":"youtube","fullUrl":""},"questionFormat":0},{"type":"quiz","question":"How does Brody die?","time":20000,"points":true,"pointsMultiplier":1,"choices":[{"answer":"Marlon Kills Her Accidentally.","correct":true},{"answer":"Bitten By A Walker","correct":false},{"answer":"Stabbed By Lilly","correct":false},{"answer":"Burned Alive","correct":false}],"image":"https://media.kahoot.it/6f603673-1670-4fe2-bbdc-d3c1e43b4e14_opt","imageMetadata":{"id":"6f603673-1670-4fe2-bbdc-d3c1e43b4e14","resources":""},"resources":"","video":{"id":"","startTime":0,"endTime":0,"service":"youtube","fullUrl":""},"questionFormat":0},{"type":"quiz","question":"The voice actress for Violet was in which 2018 film?","time":20000,"points":true,"pointsMultiplier":1,"choices":[{"answer":"Game Night","correct":false},{"answer":"The Commuter","correct":false},{"answer":"Blockers","correct":true},{"answer":"Action Point","correct":false}],"image":"https://media.kahoot.it/4ea3cc15-cb2d-4110-80a9-1f87b3399e43_opt","imageMetadata":{"id":"4ea3cc15-cb2d-4110-80a9-1f87b3399e43","resources":""},"resources":"","video":{"id":"","startTime":0,"endTime":0,"service":"youtube","fullUrl":""},"questionFormat":0},{"type":"quiz","question":"Who is the voice of Marlon?","time":20000,"points":true,"pointsMultiplier":1,"choices":[{"answer":"Ray Chase","correct":true},{"answer":"Alex Fernandez","correct":false},{"answer":"Keith Silverstein","correct":false},{"answer":"Justin Crowden","correct":false}],"image":"https://media.kahoot.it/f36f452f-c2bd-4078-8a9e-4ed6ea6e3c75_opt","imageMetadata":{"id":"f36f452f-c2bd-4078-8a9e-4ed6ea6e3c75","resources":""},"resources":"","video":{"id":"","startTime":0,"endTime":0,"service":"youtube","fullUrl":""},"questionFormat":0},{"type":"quiz","question":"Who threatens Clem and AJ after Marlon’s death?","time":20000,"points":true,"pointsMultiplier":1,"choices":[{"answer":"Louis","correct":false},{"answer":"Willy","correct":false},{"answer":"Mitch","correct":true},{"answer":"Ruby","correct":false}],"image":"https://media.kahoot.it/e64f53c5-107e-415b-a73a-1c1a8b9b7e59_opt","imageMetadata":{"id":"e64f53c5-107e-415b-a73a-1c1a8b9b7e59","resources":""},"resources":"","video":{"id":"","startTime":0,"endTime":0,"service":"youtube","fullUrl":""},"questionFormat":0},{"type":"quiz","question":"Why did James run away from his original group?","time":20000,"points":true,"pointsMultiplier":1,"choices":[{"answer":"They attacked an innocent settlement","correct":true},{"answer":"They all died","correct":false},{"answer":"He was banished","correct":false},{"answer":"They tried to kill him and he ran.","correct":false}],"image":"https://media.kahoot.it/aa197c67-f8ca-4128-9a60-17e707aef09e_opt","imageMetadata":{"id":"aa197c67-f8ca-4128-9a60-17e707aef09e","resources":""},"resources":"","video":{"id":"","startTime":0,"endTime":0,"service":"youtube","fullUrl":""},"questionFormat":0},{"type":"quiz","question":"What is Clementine’s official height?","time":20000,"points":true,"pointsMultiplier":1,"choices":[{"answer":"5’7","correct":false},{"answer":"5’4","correct":true},{"answer":"5’5","correct":false},{"answer":"5’3","correct":false}],"image":"https://media.kahoot.it/bdd31e1e-55f3-4900-adcc-f1c8c5ccf029_opt","imageMetadata":{"id":"bdd31e1e-55f3-4900-adcc-f1c8c5ccf029","resources":""},"resources":"","video":{"id":"","startTime":0,"endTime":0,"service":"youtube","fullUrl":""},"questionFormat":0},{"type":"quiz","question":"How many different kinds of Clementine can you start the game off with?","time":20000,"points":true,"pointsMultiplier":1,"choices":[{"answer":"1","correct":false},{"answer":"7","correct":false},{"answer":"5","correct":true},{"answer":"4","correct":false}],"image":"https://media.kahoot.it/56913ec5-5a82-4678-9c3f-177a1626a38e_opt","imageMetadata":{"id":"56913ec5-5a82-4678-9c3f-177a1626a38e","resources":""},"resources":"","video":{"id":"","startTime":0,"endTime":0,"service":"youtube","fullUrl":""},"questionFormat":0},{"type":"quiz","question":"Who is the last boarding school kid to introduce themselves to Clem and AJ?","time":20000,"points":true,"pointsMultiplier":1,"choices":[{"answer":"Omar","correct":false},{"answer":"Aasim","correct":false},{"answer":"Brody","correct":true},{"answer":"Louis","correct":false}],"image":"https://media.kahoot.it/c11c2317-13f1-41cd-9976-3b6e1fff7f9c_opt","imageMetadata":{"id":"c11c2317-13f1-41cd-9976-3b6e1fff7f9c","resources":""},"resources":"","video":{"id":"","startTime":0,"endTime":0,"service":"youtube","fullUrl":""},"questionFormat":0},{"type":"quiz","question":"Who does Violet blame for Sophie and Minerva’s “death”?","time":20000,"points":true,"pointsMultiplier":1,"choices":[{"answer":"Brody","correct":false},{"answer":"Marlon","correct":false},{"answer":"Clem and AJ","correct":false},{"answer":"Herself","correct":true}],"image":"https://media.kahoot.it/f6be5af2-750e-4a89-964d-6cf508744978_opt","imageMetadata":{"id":"f6be5af2-750e-4a89-964d-6cf508744978","resources":""},"resources":"","video":{"id":"","startTime":0,"endTime":0,"service":"youtube","fullUrl":""},"questionFormat":0},{"type":"quiz","question":"What is NOT one of AJ’s nicknames?","time":20000,"points":true,"pointsMultiplier":1,"choices":[{"answer":"Goofball","correct":false},{"answer":"Little Asskicker","correct":true},{"answer":"Squirt","correct":false},{"answer":"Kiddo","correct":false}],"image":"https://media.kahoot.it/5ce3593c-621c-4455-baa1-64a83a07fcc7_opt","imageMetadata":{"id":"5ce3593c-621c-4455-baa1-64a83a07fcc7","resources":""},"resources":"","video":{"id":"","startTime":0,"endTime":0,"service":"youtube","fullUrl":""},"questionFormat":0},{"type":"quiz","question":"True or False? The voice actor of Mitch has voiced Spider-Man before.","time":20000,"points":true,"pointsMultiplier":1,"choices":[{"answer":"True","correct":true},{"answer":"False","correct":false}],"image":"https://media.kahoot.it/f8ada714-59e8-486c-9c3f-c2a9c2c7966d_opt","imageMetadata":{"id":"f8ada714-59e8-486c-9c3f-c2a9c2c7966d","resources":""},"resources":"","video":{"id":"","startTime":0,"endTime":0,"service":"youtube","fullUrl":""},"questionFormat":0},{"type":"quiz","question":"Which of the following does Clem NOT need to explain to AJ?","time":20000,"points":true,"pointsMultiplier":1,"choices":[{"answer":"Romantic Couples","correct":false},{"answer":"Fishing","correct":true},{"answer":"Funerals","correct":false},{"answer":"Sleeping on a bed","correct":false}],"image":"https://media.kahoot.it/a5689cd0-e9fb-4156-8ca6-14a6aad355e0_opt","imageMetadata":{"id":"a5689cd0-e9fb-4156-8ca6-14a6aad355e0","resources":""},"resources":"","video":{"id":"","startTime":0,"endTime":0,"service":"youtube","fullUrl":""},"questionFormat":0},{"type":"quiz","question":"Who directed the first episode, “Done Running”?","time":20000,"points":true,"pointsMultiplier":1,"choices":[{"answer":"James Windeler and Adam Douglas","correct":false},{"answer":"Jessica Crause and Lauren Mee","correct":false},{"answer":"Chris Rieser and Mary Kenney","correct":false},{"answer":"Chris Rebbert and Vahram Antonian","correct":true}],"image":"https://media.kahoot.it/9ea60650-4fbf-46ab-8d2e-8059f9a2b7f6_opt","imageMetadata":{"id":"9ea60650-4fbf-46ab-8d2e-8059f9a2b7f6","resources":""},"resources":"","video":{"id":"","startTime":0,"endTime":0,"service":"youtube","fullUrl":""},"questionFormat":0},{"type":"quiz","question":"Which of the following places does Clem NOT have the option of telling Brody she would go to?","time":20000,"points":true,"pointsMultiplier":1,"choices":[{"answer":"The Coastline","correct":false},{"answer":"The Countryside","correct":true},{"answer":"The Mountains","correct":false},{"answer":"New York","correct":false}],"image":"https://media.kahoot.it/df90a3fc-534b-4d02-a403-c9b7c1ad8bbe","imageMetadata":{"id":"df90a3fc-534b-4d02-a403-c9b7c1ad8bbe","resources":""},"resources":"","video":{"id":"","startTime":0,"endTime":0,"service":"youtube","fullUrl":""},"questionFormat":0},{"type":"quiz","question":"True or False? Tenn will not forgive Marlon for giving his sisters away no matter what?","time":20000,"points":true,"pointsMultiplier":1,"choices":[{"answer":"True","correct":false},{"answer":"False","correct":true}],"image":"https://media.kahoot.it/21d79e5a-bfce-47f5-ab47-6ea4d5b014e5_opt","imageMetadata":{"id":"21d79e5a-bfce-47f5-ab47-6ea4d5b014e5","resources":""},"resources":"","video":{"id":"","startTime":0,"endTime":0,"service":"youtube","fullUrl":""},"questionFormat":0},{"type":"quiz","question":"What does Tenn claim is not scary?","time":20000,"points":true,"pointsMultiplier":1,"choices":[{"answer":"Death","correct":true},{"answer":"Walkers","correct":false},{"answer":"Bandits","correct":false},{"answer":"The Unknown","correct":false}],"image":"https://media.kahoot.it/87c91a32-4aa0-4948-8a2b-81cd9f7e8c81_opt","imageMetadata":{"id":"87c91a32-4aa0-4948-8a2b-81cd9f7e8c81","resources":""},"resources":"","video":{"id":"","startTime":0,"endTime":0,"service":"youtube","fullUrl":""},"questionFormat":0},{"type":"quiz","question":"Which of the following films has the voice actor for Aasim not have a part in?","time":20000,"points":true,"pointsMultiplier":1,"choices":[{"answer":"The Jungle Book","correct":false},{"answer":"The Last Airbender","correct":false},{"answer":"The Predator","correct":true},{"answer":"The Happening","correct":false}],"image":"https://media.kahoot.it/73c31133-375f-40fa-853d-5c94d803d3cc_opt","imageMetadata":{"id":"73c31133-375f-40fa-853d-5c94d803d3cc","resources":""},"resources":"","video":{"id":"","startTime":0,"endTime":0,"service":"youtube","fullUrl":""},"questionFormat":0},{"type":"quiz","question":"Who took over development of the last two episodes after Telltale games shut down?","time":20000,"points":true,"pointsMultiplier":1,"choices":[{"answer":"Skybound","correct":true},{"answer":"Microsoft","correct":false},{"answer":"Nintendo","correct":false},{"answer":"Sony","correct":false}],"image":"https://media.kahoot.it/f41cee8b-547f-4c15-96d7-25dee519f6ca_opt","imageMetadata":{"id":"f41cee8b-547f-4c15-96d7-25dee519f6ca","resources":""},"resources":"","video":{"id":"","startTime":0,"endTime":0,"service":"youtube","fullUrl":""},"questionFormat":0},{"type":"quiz","question":"In episode 3, who does Willy blame for Mitch's death?","time":20000,"points":true,"pointsMultiplier":1,"choices":[{"answer":"Louis/Violet","correct":false},{"answer":"AJ","correct":false},{"answer":"Tenn","correct":true},{"answer":"Clementine","correct":false}],"image":"","resources":"","video":{"id":"","startTime":0,"endTime":0,"service":"youtube","fullUrl":""},"questionFormat":0}],"answerMap":[4,4,4,4,4,4,4,4,4,4,4,4,4,4,4,4,4,4,4,4,4,4,4,4,4,4,4,4,4,4,4,4,4,4,4,4,4,2,4,4,4,2,4,4,4,4],"uuid":"6801dece-f935-450f-b823-01a540d9aa6d"}