{"author":"FrauGoble","questions":[{"type":"quiz","question":"Wie ist das Wetter?","time":10000,"points":true,"pointsMultiplier":1,"choices":[{"answer":"Es gibt Gewitter","correct":true},{"answer":"Esgibt Regenbogen","correct":false},{"answer":"Es hagelt","correct":false},{"answer":"Es ist nebelig","correct":false}],"image":"http://s3-eu-west-1.amazonaws.com/lecturequizuploads/2cab7762-79d5-43d1-b815-48372897abac_opt","imageMetadata":{"id":"2cab7762-79d5-43d1-b815-48372897abac"},"video":{"id":"","startTime":0,"endTime":0,"service":"youtube"},"questionFormat":0},{"type":"quiz","question":"Wie ist das Wetter?","time":10000,"points":true,"pointsMultiplier":1,"choices":[{"answer":"Es blitzt","correct":false},{"answer":"Es donnert. ","correct":false},{"answer":"Es schneit","correct":false},{"answer":"die Sonne scheint","correct":true}],"image":"http://s3-eu-west-1.amazonaws.com/lecturequizuploads/4b6a2a9f-22c1-442a-9cbd-4760872e3850_opt","imageMetadata":{"id":"4b6a2a9f-22c1-442a-9cbd-4760872e3850"},"video":{"id":"","startTime":0,"endTime":0,"service":"youtube"},"questionFormat":0},{"type":"quiz","question":"Wie ist das Wetter?","time":10000,"points":true,"pointsMultiplier":1,"choices":[{"answer":"Es regnet","correct":false},{"answer":"Es ist Winter","correct":false},{"answer":"Es gibt einen Regenbogen","correct":true},{"answer":"Es donnert","correct":false}],"image":"http://s3-eu-west-1.amazonaws.com/lecturequizuploads/cc0ba14b-307a-44bb-868c-f43b5a01e734_opt","imageMetadata":{"id":"cc0ba14b-307a-44bb-868c-f43b5a01e734"},"video":{"id":"","startTime":0,"endTime":0,"service":"youtube"},"questionFormat":0},{"type":"quiz","question":"Wie ist das Wetter?","time":10000,"points":true,"pointsMultiplier":1,"choices":[{"answer":"Es ist nebelig","correct":true},{"answer":"Es ist regnerisch","correct":false},{"answer":"Es ist schwül","correct":false},{"answer":"Es ist schön","correct":false}],"image":"http://s3-eu-west-1.amazonaws.com/lecturequizuploads/937f4ab0-75f2-43a6-8a3b-aa4a9cb7763e_opt","imageMetadata":{"id":"937f4ab0-75f2-43a6-8a3b-aa4a9cb7763e"},"video":{"id":"","startTime":0,"endTime":0,"service":"youtube"},"questionFormat":0},{"type":"quiz","question":"Wie ist das Wetter?","time":10000,"points":true,"pointsMultiplier":1,"choices":[{"answer":"Es ist schön","correct":false},{"answer":"Es ist warm","correct":false},{"answer":"Es ist Winter","correct":false},{"answer":"Es ist windig","correct":true}],"image":"http://s3-eu-west-1.amazonaws.com/lecturequizuploads/4af305a1-63dd-478e-9101-85b3cb2310ad_opt","imageMetadata":{"id":"4af305a1-63dd-478e-9101-85b3cb2310ad"},"video":{"id":"","startTime":0,"endTime":0,"service":"youtube"},"questionFormat":0},{"type":"quiz","question":"Wie ist das Wetter?","time":10000,"points":true,"pointsMultiplier":1,"choices":[{"answer":"Es ist windig","correct":false},{"answer":"Es ist wolkig","correct":false},{"answer":"Es ist heiβ","correct":true},{"answer":"häβlch","correct":false}],"image":"http://s3-eu-west-1.amazonaws.com/lecturequizuploads/89c0d935-ee82-4446-928e-e49667b3dffa_opt","imageMetadata":{"id":"89c0d935-ee82-4446-928e-e49667b3dffa"},"video":{"id":"","startTime":0,"endTime":0,"service":"youtube"},"questionFormat":0},{"type":"quiz","question":"Wie ist das Wetter?","time":10000,"points":true,"pointsMultiplier":1,"choices":[{"answer":"Es scheint","correct":false},{"answer":"Es schneit","correct":true},{"answer":"Es hagelt","correct":false},{"answer":"Es ist regnerisch","correct":false}],"image":"http://s3-eu-west-1.amazonaws.com/lecturequizuploads/c377ff43-88fc-4ab8-b3da-04408ea997fb_opt","imageMetadata":{"id":"c377ff43-88fc-4ab8-b3da-04408ea997fb"},"video":{"id":"","startTime":0,"endTime":0,"service":"youtube"},"questionFormat":0},{"type":"quiz","question":"Wie ist das Wetter?","time":10000,"points":true,"pointsMultiplier":1,"choices":[{"answer":"Es ist häβlch","correct":false},{"answer":"Es ist kalt","correct":true},{"answer":"Es ist warm","correct":false},{"answer":"Es ist schön","correct":false}],"image":"http://s3-eu-west-1.amazonaws.com/lecturequizuploads/9dad78a1-aa98-40fc-9620-85201d9a154e_opt","imageMetadata":{"id":"9dad78a1-aa98-40fc-9620-85201d9a154e"},"video":{"id":"","startTime":0,"endTime":0,"service":"youtube"},"questionFormat":0},{"type":"quiz","question":"Wann ist das?","time":10000,"points":true,"pointsMultiplier":1,"choices":[{"answer":"Es ist Sommer","correct":false},{"answer":"Es ist Winter","correct":false},{"answer":"Es ist Herbst","correct":true},{"answer":"Es ist Frühling","correct":false}],"image":"http://s3-eu-west-1.amazonaws.com/lecturequizuploads/c6043b6e-f2de-4e63-a3d7-d4b5521e38ef_opt","imageMetadata":{"id":"c6043b6e-f2de-4e63-a3d7-d4b5521e38ef"},"video":{"id":"","startTime":0,"endTime":0,"service":"youtube"},"questionFormat":0},{"type":"quiz","question":"Wann ist das?","time":10000,"points":true,"pointsMultiplier":1,"choices":[{"answer":"Es ist Frühling","correct":true},{"answer":"Es ist Herbst","correct":false},{"answer":"Es ist Sommer","correct":false},{"answer":"Es ist Winter","correct":false}],"image":"http://s3-eu-west-1.amazonaws.com/lecturequizuploads/81044699-a0b5-42fa-882c-4f9da4dea6b3_opt","imageMetadata":{"id":"81044699-a0b5-42fa-882c-4f9da4dea6b3"},"video":{"id":"","startTime":0,"endTime":0,"service":"youtube"},"questionFormat":0},{"type":"quiz","question":"Wie ist das Wetter?","time":10000,"points":true,"pointsMultiplier":1,"choices":[{"answer":"Es ist windig","correct":false},{"answer":"Es ist wolkig","correct":true},{"answer":"Es ist Winter","correct":false},{"answer":"Es ist nebelig","correct":false}],"image":"http://s3-eu-west-1.amazonaws.com/lecturequizuploads/f7d7f397-b201-414c-8d57-a1c6a9d92ee8_opt","imageMetadata":{"id":"f7d7f397-b201-414c-8d57-a1c6a9d92ee8"},"video":{"id":"","startTime":0,"endTime":0,"service":"youtube"},"questionFormat":0},{"type":"quiz","question":"Wie ist das Wetter?","time":10000,"points":true,"pointsMultiplier":1,"choices":[{"answer":"Es gibt Gewittter","correct":false},{"answer":"Es gibt Donner","correct":false},{"answer":"Es regnet","correct":true},{"answer":"Es ist nebelig","correct":false}],"image":"http://s3-eu-west-1.amazonaws.com/lecturequizuploads/1cae7155-383b-4671-abfb-a97568afa62a_opt","imageMetadata":{"id":"1cae7155-383b-4671-abfb-a97568afa62a"},"video":{"id":"","startTime":0,"endTime":0,"service":"youtube"},"questionFormat":0}],"answerMap":[4,4,4,4,4,4,4,4,4,4,4,4],"uuid":"7f53e75d-aae9-45f7-ae2d-dfb1bfcee854"}