{"answerMap":[4,4,4,4,4,4,4,4,4,4,4,4,4,4],"uuid":"7ff9f34a-bf75-4da9-8f3b-d27577ef27b0","author":"EHamon","questions":[{"video":{"fullUrl":"","endTime":0,"startTime":0,"id":"","service":"youtube"},"time":30000,"pointsMultiplier":0,"choices":[{"answer":"Have you spotted the elephant in the room?","correct":false},{"correct":false,"answer":"Should I mention the elephant in the room?"},{"answer":"Still, I am stiller than you.","correct":false},{"correct":true,"answer":"It does not matter how still you are, Ben is stiller."}],"points":false,"question":"Auf Deutsch?","questionFormat":0,"resources":"","type":"quiz","image":"https://media.kahoot.it/bffd8c8d-3d5f-43ba-90f7-532bb17b8ae5_opt","imageMetadata":{"id":"bffd8c8d-3d5f-43ba-90f7-532bb17b8ae5","resources":""}},{"resources":"","time":30000,"imageMetadata":{"resources":"","id":"1b5716d1-a4f0-435e-812f-b86ed9768f42"},"points":true,"question":"Dein Ernst?","pointsMultiplier":1,"type":"quiz","questionFormat":0,"choices":[{"answer":"Honestly?","correct":false},{"correct":true,"answer":"Are you being serious?"},{"answer":"Really?","correct":false},{"correct":false,"answer":"What do you mean?"}],"image":"https://media.kahoot.it/1b5716d1-a4f0-435e-812f-b86ed9768f42_opt","video":{"service":"youtube","startTime":0,"id":"","endTime":0,"fullUrl":""}},{"time":30000,"type":"quiz","imageMetadata":{"id":"e36b896e-fc3b-48d0-8813-29b8791e6ec0","resources":""},"question":"Ich glaube tatsächlich, Deutsch ist eine schöne Sprache","video":{"fullUrl":"","id":"","service":"youtube","endTime":0,"startTime":0},"points":true,"pointsMultiplier":1,"questionFormat":0,"image":"https://media.kahoot.it/e36b896e-fc3b-48d0-8813-29b8791e6ec0_opt","choices":[{"answer":"I genuinely think that German is a pretty language.","correct":true},{"correct":false,"answer":"I really find German very boring."},{"answer":"German is the best language in the world.","correct":false},{"answer":"Put your German smile on.","correct":false}],"resources":""},{"type":"quiz","question":"Deutsch ist sehr unterhaltsam.","pointsMultiplier":1,"imageMetadata":{"id":"1799be17-a6c0-413a-9cdd-fc563c4b99c6","resources":""},"image":"https://media.kahoot.it/1799be17-a6c0-413a-9cdd-fc563c4b99c6_opt","resources":"","time":30000,"questionFormat":0,"video":{"id":"","service":"youtube","fullUrl":"","endTime":0,"startTime":0},"points":true,"choices":[{"correct":false,"answer":"German is very impressive."},{"correct":false,"answer":"German is very amusing."},{"answer":"German is very nice.","correct":false},{"correct":true,"answer":"German is very entertaining."}]},{"resources":"","choices":[{"answer":"German? What do you mean?","correct":false},{"answer":"German? What do you mean?","correct":false},{"answer":"German? What is that?","correct":true},{"correct":false,"answer":"German? What are you saying?"}],"time":30000,"video":{"id":"","fullUrl":"","endTime":0,"service":"youtube","startTime":0},"image":"https://media.kahoot.it/0ff25b0f-731c-4434-a153-cdb8c755337e_opt","question":"Deutsch? Was ist das?","imageMetadata":{"id":"0ff25b0f-731c-4434-a153-cdb8c755337e","resources":""},"type":"quiz","points":true,"questionFormat":0,"pointsMultiplier":1},{"imageMetadata":{"id":"8fa6e2d8-b841-421d-9eac-cee2159903d1","resources":""},"points":true,"video":{"endTime":0,"fullUrl":"","id":"","startTime":0,"service":"youtube"},"question":"Faszinierend","pointsMultiplier":1,"resources":"","time":30000,"type":"quiz","image":"https://media.kahoot.it/8fa6e2d8-b841-421d-9eac-cee2159903d1_opt","choices":[{"correct":false,"answer":"Amazing"},{"answer":"Fascinating","correct":true},{"answer":"Brilliant","correct":false},{"correct":false,"answer":"Impressive"}],"questionFormat":0},{"pointsMultiplier":1,"video":{"startTime":0,"fullUrl":"","endTime":0,"id":"","service":"youtube"},"question":"Gib dem Mann einen Keks!","time":30000,"questionFormat":0,"imageMetadata":{"id":"322e05c8-c769-4ece-8b40-921394fedcc7","resources":""},"points":true,"image":"https://media.kahoot.it/322e05c8-c769-4ece-8b40-921394fedcc7_opt","resources":"","choices":[{"correct":true,"answer":"Give this man a biscuit!"},{"correct":false,"answer":"Give this man a shave!"},{"answer":"Give this man five!","correct":false},{"correct":false,"answer":"Give this man a voice!"}],"type":"quiz"},{"question":"Ich habe alles vergessen!!","imageMetadata":{"id":"dc80d104-49e5-48b7-aafd-673bec00480f","resources":""},"points":true,"choices":[{"correct":false,"answer":"I destroyed everything!"},{"answer":"I burnt everything!","correct":false},{"answer":"I lost everything!","correct":false},{"correct":true,"answer":"I forgot everything!"}],"image":"https://media.kahoot.it/dc80d104-49e5-48b7-aafd-673bec00480f_opt","video":{"id":"","fullUrl":"","service":"youtube","startTime":0,"endTime":0},"type":"quiz","pointsMultiplier":1,"questionFormat":0,"time":30000,"resources":""},{"choices":[{"answer":"I have it on!","correct":false},{"answer":"I have what it takes!","correct":true},{"answer":"I have it all!","correct":false},{"answer":"I am hungry!","correct":false}],"questionFormat":0,"question":"Ich habe es drauf!","imageMetadata":{"id":"be4bfff4-d30b-4995-80db-a2b27d3ca453","resources":""},"pointsMultiplier":1,"image":"https://media.kahoot.it/be4bfff4-d30b-4995-80db-a2b27d3ca453","time":30000,"resources":"","video":{"endTime":0,"id":"","fullUrl":"","service":"youtube","startTime":0},"points":true,"type":"quiz"},{"questionFormat":0,"pointsMultiplier":1,"image":"https://media.kahoot.it/ed665a75-1883-44dd-ad10-b60cc4280095_opt","points":true,"question":"Ich hab, ich habe Style und Geld!","resources":"","video":{"fullUrl":"","endTime":0,"startTime":0,"service":"youtube","id":""},"choices":[{"answer":"I have style and money!","correct":true},{"answer":"I have style and gold!","correct":false},{"correct":false,"answer":"I have style and hands!"},{"correct":false,"answer":"I have style and ideas!"}],"time":30000,"imageMetadata":{"resources":"","id":"ed665a75-1883-44dd-ad10-b60cc4280095"},"type":"quiz"},{"image":"https://media.kahoot.it/d2383a60-e190-4291-b04e-6ed2377eee7b_opt","points":true,"question":"Boah... Ich hotze gleich.","pointsMultiplier":1,"imageMetadata":{"id":"d2383a60-e190-4291-b04e-6ed2377eee7b","resources":""},"questionFormat":0,"choices":[{"answer":"Er, let me think...","correct":false},{"correct":false,"answer":"Er, wait a minute..."},{"correct":true,"answer":"Er, I feel sick..."},{"answer":"Er, I can't think...","correct":false}],"type":"quiz","resources":"","time":30000,"video":{"service":"youtube","fullUrl":"","startTime":0,"endTime":0,"id":""}},{"video":{"service":"youtube","id":"","endTime":0,"startTime":0,"fullUrl":""},"question":"Ich vermisse dich so sehr.","points":true,"pointsMultiplier":1,"imageMetadata":{"resources":"","id":"7cbeb013-c9fd-4aa3-88a0-7a5287a4c1f1"},"type":"quiz","time":30000,"questionFormat":0,"resources":"","choices":[{"answer":"I like you so much.","correct":false},{"answer":"I miss you so much.","correct":true},{"answer":"I despise you so much.","correct":false},{"answer":"I envy you so much.","correct":false}],"image":"https://media.kahoot.it/7cbeb013-c9fd-4aa3-88a0-7a5287a4c1f1_opt"},{"type":"quiz","questionFormat":0,"time":30000,"points":true,"resources":"","question":"Oh Gott, ich glaube ich werde gleich fotografiert.","imageMetadata":{"id":"1cbc107a-f851-4d45-b367-12a73cea387c","resources":""},"image":"https://media.kahoot.it/1cbc107a-f851-4d45-b367-12a73cea387c_opt","video":{"fullUrl":"","id":"","endTime":0,"startTime":0,"service":"youtube"},"choices":[{"answer":"Oh God, I think they are just about to take my photo!","correct":true},{"answer":"Oh God, I can't believe this!","correct":false},{"answer":"Oh God, I think I really have to take a photo of this!","correct":false},{"answer":"Oh God, I think this photo will be dreadful!","correct":false}],"pointsMultiplier":1},{"choices":[{"answer":"Zayn Malik leaves 1D... what a disaster.","correct":false},{"correct":false,"answer":"Zayn Malik leaves 1D... I set his house on fire."},{"answer":"Zayn Malik leaves 1D... I took care of him.","correct":true},{"correct":false,"answer":"Zayn Malik leaves 1D... can anything worse happen?"}],"time":30000,"resources":"","imageMetadata":{"id":"7cac7c48-9f69-4869-b3f9-46212e6b082b","resources":""},"pointsMultiplier":1,"points":true,"image":"https://media.kahoot.it/7cac7c48-9f69-4869-b3f9-46212e6b082b_opt","video":{"endTime":0,"startTime":0,"service":"youtube","fullUrl":"","id":""},"questionFormat":0,"question":"Zayn Malik verlässt One Direction... Hab mich um ihn gekümmert.","type":"quiz"}]}