{"author":"AFFabian","questions":[{"type":"quiz","question":"Functions or modules found in other languages are similar to____in C#","time":30000,"points":true,"pointsMultiplier":1,"choices":[{"answer":"modifiers","correct":false},{"answer":"parameters","correct":false},{"answer":"arguments","correct":false},{"answer":"methods","correct":true}],"layout":"CLASSIC","resources":"","video":{"startTime":0,"endTime":0,"service":"youtube","fullUrl":""},"questionFormat":0},{"type":"quiz","question":"Which of the following is placed in a method heading to indicate that no value will be returned?","time":20000,"points":true,"pointsMultiplier":1,"choices":[{"answer":"public","correct":false},{"answer":"static","correct":false},{"answer":"arguments","correct":false},{"answer":"void","correct":true}],"layout":"CLASSIC","resources":"","video":{"startTime":0,"endTime":0,"service":"youtube","fullUrl":""},"questionFormat":0},{"type":"quiz","question":"Which of the following modifiers is the most restrictive?","time":20000,"points":true,"pointsMultiplier":1,"choices":[{"answer":"private","correct":true},{"answer":"super public ","correct":false},{"answer":"public","correct":false},{"answer":"super C#","correct":false}],"layout":"CLASSIC","resources":"","video":{"startTime":0,"endTime":0,"service":"youtube","fullUrl":""},"questionFormat":0},{"type":"quiz","question":"Which of the following identifiers follows the standard naming convention for a method?","time":20000,"points":true,"pointsMultiplier":1,"choices":[{"answer":"PrintReport","correct":true},{"answer":"Calculate Final Grade","correct":false},{"answer":"2 Method1","correct":false},{"answer":"MilesP erGallon","correct":false}],"layout":"CLASSIC","resources":"","video":{"startTime":0,"endTime":0,"service":"youtube","fullUrl":""},"questionFormat":0},{"type":"quiz","question":"Which of the following statements are correct about functions?","time":20000,"points":true,"pointsMultiplier":1,"choices":[{"answer":"C# allows a function to have arguments with default values","correct":true},{"answer":"Redefining a method parameter in the method’s body causes an exception","correct":false},{"answer":"Omitting the return type in method definition results into exception","correct":false},{"answer":"C# allows function to have arguments with default values","correct":false}],"layout":"CLASSIC","resources":"","video":{"startTime":0,"endTime":0,"service":"youtube","fullUrl":""},"questionFormat":0},{"type":"quiz","question":"What will be the output of the following C# code?","time":20000,"points":true,"pointsMultiplier":1,"choices":[{"answer":"4 3 3","correct":false},{"answer":"&nbsp;4 4 3","correct":false},{"answer":"4 3 4","correct":true},{"answer":"3 4 4","correct":false}],"layout":"CLASSIC","image":"https://media.kahoot.it/47fa24a4-3db8-4da8-b892-1f243d3ea0cf","imageMetadata":{"id":"47fa24a4-3db8-4da8-b892-1f243d3ea0cf","contentType":"image/png","width":1016,"height":874,"resources":""},"resources":"","video":{"startTime":0,"endTime":0,"service":"youtube","fullUrl":""},"questionFormat":0},{"type":"quiz","question":"&nbsp;When a function fun() is to receive an int, a single &amp; a double and it is to return a decimal, then the correct way of ","time":20000,"points":true,"pointsMultiplier":1,"choices":[{"answer":"static fun(int i, single j, double k){returndecimal;}","correct":false},{"answer":"static decimal fun(int i, single, double k){} ","correct":true},{"answer":"decimal fun(int i, single j, double k){}","correct":false},{"answer":"decimal static fun(int i, single j, double k){}","correct":false}],"layout":"CLASSIC","resources":"","video":{"startTime":0,"endTime":0,"service":"youtube","fullUrl":""},"questionFormat":0},{"type":"quiz","question":"Which of the following is a GPU?","time":20000,"points":true,"pointsMultiplier":1,"choices":[{"answer":"Intel Xeon","correct":false},{"answer":"AMD Ryzen 9","correct":false},{"answer":"Central Processing Unit","correct":false},{"answer":"Radeon RX 570 DirectX 12 AXRX&nbsp;","correct":true}],"layout":"CLASSIC","resources":"","video":{"startTime":0,"endTime":0,"service":"youtube","fullUrl":""},"questionFormat":0}],"answerMap":[4,4,4,4,4,4,4,4],"uuid":"8c561dc8-c9df-43bc-a318-e174f0dd1004"}