{"author":"ssiukonen","questions":[{"type":"jumble","question":"Ole stellt fest,","time":60000,"points":true,"pointsMultiplier":1,"choices":[{"answer":"dass","correct":true},{"answer":"der Ticketkauf","correct":true},{"answer":"schwierig","correct":true},{"answer":"ist","correct":true}],"image":"","resources":"","video":{"id":"","startTime":0,"endTime":0,"service":"youtube","fullUrl":""},"questionFormat":0},{"type":"jumble","question":"Weißt du,","time":60000,"points":true,"pointsMultiplier":1,"choices":[{"answer":"dass","correct":true},{"answer":"ich","correct":true},{"answer":"nach Wien","correct":true},{"answer":"fahre","correct":true}],"image":"","resources":"","video":{"id":"","startTime":0,"endTime":0,"service":"youtube","fullUrl":""},"questionFormat":0},{"type":"jumble","question":"Ich gehe nicht zur Schule,","time":60000,"points":true,"pointsMultiplier":1,"choices":[{"answer":"weil","correct":true},{"answer":"ich","correct":true},{"answer":"krank","correct":true},{"answer":"bin","correct":true}],"image":"","resources":"","video":{"id":"","startTime":0,"endTime":0,"service":"youtube","fullUrl":""},"questionFormat":0},{"type":"jumble","question":"Wenn ich mein Zimmer aufräume,","time":60000,"points":true,"pointsMultiplier":1,"choices":[{"answer":"bekomme","correct":true},{"answer":"ich","correct":true},{"answer":"mehr","correct":true},{"answer":"Taschengeld","correct":true}],"image":"","resources":"","video":{"id":"","startTime":0,"endTime":0,"service":"youtube","fullUrl":""},"questionFormat":0},{"type":"jumble","question":"Ole hat Tom versprochen,","time":60000,"points":true,"pointsMultiplier":1,"choices":[{"answer":"dass","correct":true},{"answer":"er","correct":true},{"answer":"das Geld","correct":true},{"answer":"zurückzahlt","correct":true}],"image":"","resources":"","video":{"id":"","startTime":0,"endTime":0,"service":"youtube","fullUrl":""},"questionFormat":0},{"type":"jumble","question":"Ich bin satt,","time":60000,"points":true,"pointsMultiplier":1,"choices":[{"answer":"weil","correct":true},{"answer":"ich","correct":true},{"answer":"gegessen","correct":true},{"answer":"habe","correct":true}],"image":"","resources":"","video":{"id":"","startTime":0,"endTime":0,"service":"youtube","fullUrl":""},"questionFormat":0},{"type":"jumble","question":"Wenn Justyna eine Fahrkarte kauft,","time":60000,"points":true,"pointsMultiplier":1,"choices":[{"answer":"kann","correct":true},{"answer":"sie","correct":true},{"answer":"nach Österreich","correct":true},{"answer":"fahren","correct":true}],"image":"","resources":"","video":{"id":"","startTime":0,"endTime":0,"service":"youtube","fullUrl":""},"questionFormat":0},{"type":"jumble","question":"Der Zug fährt zuerst um 15 Uhr ab,","time":60000,"points":true,"pointsMultiplier":1,"choices":[{"answer":"weil","correct":true},{"answer":"er","correct":true},{"answer":"eine Verspätung","correct":true},{"answer":"hat","correct":true}],"image":"","resources":"","video":{"id":"","startTime":0,"endTime":0,"service":"youtube","fullUrl":""},"questionFormat":0}],"answerMap":[4,4,4,4,4,4,4,4],"uuid":"90528489-144b-4152-a692-8deec7ed4cc0"}