{"author":"eleizaldemusika","questions":[{"type":"quiz","question":"Gatiburen  bideoklip honetako abestiaren izena zein da?","time":20000,"points":true,"pointsMultiplier":1,"choices":[{"answer":"Musturrek sartunde","correct":false},{"answer":"Euritan dantzan","correct":true},{"answer":"Ez dot sinisten","correct":false},{"answer":"Doniene","correct":false}],"image":"http://s3-eu-west-1.amazonaws.com/lecturequizuploads/8b0403f2-2397-40b8-8997-894777150ac4_opt","imageMetadata":{"id":"8b0403f2-2397-40b8-8997-894777150ac4","resources":""},"resources":"","video":{"id":"","startTime":0,"endTime":0,"service":"youtube","fullUrl":""},"questionFormat":0},{"type":"quiz","question":"Zein ez da ITOIZ taldearen abestia?","time":20000,"points":true,"pointsMultiplier":1,"choices":[{"answer":"Lo egin","correct":false},{"answer":"Hegal egiten","correct":false},{"answer":"Lau teilatu","correct":false},{"answer":"Haika mutil","correct":true}],"image":"http://s3-eu-west-1.amazonaws.com/lecturequizuploads/ba942b8b-98ee-4fea-8319-ca309324cc4d_opt","imageMetadata":{"id":"ba942b8b-98ee-4fea-8319-ca309324cc4d","resources":""},"resources":"","video":{"id":"","startTime":0,"endTime":0,"service":"youtube","fullUrl":""},"questionFormat":0},{"type":"quiz","question":"Norena da \"Izarren hautsa\" abestia?","time":20000,"points":true,"pointsMultiplier":1,"choices":[{"answer":"Mikel Laboa","correct":false},{"answer":"Benito Lertxundi","correct":false},{"answer":"Mikel Urdangarin","correct":false},{"answer":"Xabier Lete","correct":true}],"image":"","resources":"","video":{"id":"","startTime":0,"endTime":0,"service":"youtube","fullUrl":""},"questionFormat":0},{"type":"quiz","question":"Non jaio zan Juan Crisóstomo Arriaga, musikari euskalduna?","time":20000,"points":true,"pointsMultiplier":1,"choices":[{"answer":"Donostia","correct":false},{"answer":"Iruñea","correct":false},{"answer":"Gernika","correct":false},{"answer":"Bilbo","correct":true}],"image":"http://s3-eu-west-1.amazonaws.com/lecturequizuploads/c995d898-ece6-471e-ab2c-d2fb3e660e29_opt","imageMetadata":{"id":"c995d898-ece6-471e-ab2c-d2fb3e660e29","resources":""},"resources":"","video":{"id":"","startTime":0,"endTime":0,"service":"youtube","fullUrl":""},"questionFormat":0},{"type":"quiz","question":"Nor ez zan \"Ez dok amairu\" taldeko partaidea?","time":20000,"points":true,"pointsMultiplier":1,"choices":[{"answer":"Benito Lertxundi","correct":false},{"answer":"Xabier Lete","correct":false},{"answer":"Mikel Markez","correct":true},{"answer":"Lourdes Iriondo","correct":false}],"image":"http://s3-eu-west-1.amazonaws.com/lecturequizuploads/b2635e77-0017-4567-bfee-d20ef99ded50_opt","imageMetadata":{"id":"b2635e77-0017-4567-bfee-d20ef99ded50","resources":""},"resources":"","video":{"id":"","startTime":0,"endTime":0,"service":"youtube","fullUrl":""},"questionFormat":0},{"type":"quiz","question":"Zelan jarraitzen dau abesti honek: AUPA GIZONA, JEIKI MUTIL...","time":20000,"points":true,"pointsMultiplier":1,"choices":[{"answer":"Irrintzi bat dabil","correct":false},{"answer":"aupa herria","correct":false},{"answer":"atzar emazte ta neskatil","correct":true},{"answer":"txistua eta danbolin","correct":false}],"image":"","resources":"","video":{"id":"","startTime":0,"endTime":0,"service":"youtube","fullUrl":""},"questionFormat":0},{"type":"quiz","question":"Nork konposatu eban \"GERNIKAKO ARBOLA\" ?","time":20000,"points":true,"pointsMultiplier":1,"choices":[{"answer":"Arriaga","correct":false},{"answer":"Guridi","correct":false},{"answer":"Iparragirre","correct":true},{"answer":"Iñigito txapelpunk","correct":false}],"image":"","resources":"","video":{"id":"","startTime":0,"endTime":0,"service":"youtube","fullUrl":""},"questionFormat":0},{"type":"quiz","question":"Ze taldeko kidea da Xabier Solano?","time":20000,"points":true,"pointsMultiplier":1,"choices":[{"answer":"Berritxarrak","correct":false},{"answer":"Gatibu","correct":false},{"answer":"Ken7","correct":false},{"answer":"Esne Beltza","correct":true}],"image":"http://s3-eu-west-1.amazonaws.com/lecturequizuploads/d26bc609-6167-42dc-96ff-de68fd6b8bcb_opt","imageMetadata":{"id":"d26bc609-6167-42dc-96ff-de68fd6b8bcb","resources":""},"resources":"","video":{"id":"","startTime":0,"endTime":0,"service":"youtube","fullUrl":""},"questionFormat":0},{"type":"quiz","question":"Nork konposatu eban \"EL CASERIO\" zarzuela?","time":20000,"points":true,"pointsMultiplier":1,"choices":[{"answer":"Ravel","correct":false},{"answer":"Sarasate","correct":false},{"answer":"Guridi","correct":true},{"answer":"Arriaga","correct":false}],"image":"","resources":"","video":{"id":"","startTime":0,"endTime":0,"service":"youtube","fullUrl":""},"questionFormat":0},{"type":"quiz","question":"Nork idatzi eban BERMEOKO PORTUAN abestia?","time":20000,"points":true,"pointsMultiplier":1,"choices":[{"answer":"Jose Antonio Egia","correct":false},{"answer":"Ezezaguna","correct":true},{"answer":"Jose Antonio Erauzkin","correct":false},{"answer":"Iparragirre","correct":false}],"image":"","resources":"","video":{"id":"","startTime":0,"endTime":0,"service":"youtube","fullUrl":""},"questionFormat":0}],"answerMap":[4,4,4,4,4,4,4,4,4,4],"uuid":"f8b2ca16-730e-499b-97ae-0ef794ec9857"}