{"author":"marcyrobinson","questions":[{"type":"quiz","question":"The measurement of how much matter an object contains is its","time":20000,"points":true,"pointsMultiplier":1,"choices":[{"answer":"melting point","correct":false},{"answer":"mass","correct":true},{"answer":"volume","correct":false},{"answer":"weight","correct":false}],"image":"http://s3-eu-west-1.amazonaws.com/lecturequizuploads/c84007dd-4e02-460a-8f7d-402dc363ccb1_opt","imageMetadata":{"id":"c84007dd-4e02-460a-8f7d-402dc363ccb1","resources":""},"resources":"","video":{"id":"","startTime":0,"endTime":0,"service":"youtube","fullUrl":""},"questionFormat":0},{"type":"quiz","question":"After completing an experiment, all chemical wastes&nbsp;should be","time":20000,"points":true,"pointsMultiplier":1,"choices":[{"answer":"left at your lab station for the next class.","correct":false},{"answer":"disposed of in the sink.","correct":false},{"answer":"disposed of according to your instructor’s directions.","correct":true},{"answer":"taken home.","correct":false}],"image":"http://s3-eu-west-1.amazonaws.com/lecturequizuploads/3e1a8094-b299-4054-889a-6207662530b6_opt","imageMetadata":{"id":"3e1a8094-b299-4054-889a-6207662530b6","resources":""},"resources":"","video":{"id":"","startTime":0,"endTime":0,"service":"youtube","fullUrl":""},"questionFormat":0},{"type":"quiz","question":"Anything that has mass and takes up space is called","time":20000,"points":true,"pointsMultiplier":1,"choices":[{"answer":"homogeneous.","correct":false},{"answer":"matter.","correct":true},{"answer":"energy.","correct":false},{"answer":"heterogeneous.","correct":false}],"image":"http://s3-eu-west-1.amazonaws.com/lecturequizuploads/ff5e031c-9476-4e2d-a5d7-3bc990e2b949","imageMetadata":{"id":"ff5e031c-9476-4e2d-a5d7-3bc990e2b949","resources":""},"resources":"","video":{"id":"","startTime":0,"endTime":0,"service":"youtube","fullUrl":""},"questionFormat":0},{"type":"quiz","question":"In the laboratory, volumes of liquid are usually measured with a(n)","time":20000,"points":true,"pointsMultiplier":1,"choices":[{"answer":"triple-beam balance.","correct":false},{"answer":"electrode.","correct":false},{"answer":"scale.","correct":false},{"answer":"graduated cylinder.","correct":true}],"image":"https://media.kahoot.it/0e5a8239-0e9a-4658-840c-395085e21df6_opt","imageMetadata":{"id":"0e5a8239-0e9a-4658-840c-395085e21df6","resources":""},"resources":"","video":{"id":"","startTime":0,"endTime":0,"service":"youtube","fullUrl":""},"questionFormat":0},{"type":"quiz","question":"Who is responsible for safety in a science lab?","time":20000,"points":true,"pointsMultiplier":1,"choices":[{"answer":"the principal","correct":false},{"answer":"everyone","correct":true},{"answer":"the teacher","correct":false},{"answer":"the custodian","correct":false}],"image":"http://s3-eu-west-1.amazonaws.com/lecturequizuploads/f0ddaa3b-8641-4b82-8c3e-1aa42a0f0ed1_opt","imageMetadata":{"id":"f0ddaa3b-8641-4b82-8c3e-1aa42a0f0ed1","resources":""},"resources":"","video":{"id":"","startTime":0,"endTime":0,"service":"youtube","fullUrl":""},"questionFormat":0},{"type":"quiz","question":"The measurement of how much mass is contained in a given volume is called","time":20000,"points":true,"pointsMultiplier":1,"choices":[{"answer":"density.","correct":true},{"answer":"weight.","correct":false},{"answer":"melting point.","correct":false},{"answer":"boiling point.","correct":false}],"image":"http://s3-eu-west-1.amazonaws.com/lecturequizuploads/9854aca3-b792-4c78-839b-a1765a3b485c_opt","imageMetadata":{"id":"9854aca3-b792-4c78-839b-a1765a3b485c","resources":""},"resources":"","video":{"id":"","startTime":0,"endTime":0,"service":"youtube","fullUrl":""},"questionFormat":0},{"type":"quiz","question":"Which process represents freezing?","time":20000,"points":true,"pointsMultiplier":1,"choices":[{"answer":"gas to liquid","correct":false},{"answer":"liquid to solid","correct":true},{"answer":"solid to liquid","correct":false},{"answer":"liquid to gas","correct":false}],"image":"http://s3-eu-west-1.amazonaws.com/lecturequizuploads/48b70ef4-2594-408d-bc71-2bfd5991fcca_opt","imageMetadata":{"id":"48b70ef4-2594-408d-bc71-2bfd5991fcca","resources":""},"resources":"","video":{"id":"","startTime":0,"endTime":0,"service":"youtube","fullUrl":""},"questionFormat":0},{"type":"quiz","question":"The layer that is most dense would be located&nbsp;","time":20000,"points":true,"pointsMultiplier":1,"choices":[{"answer":"at the top of the jar","correct":false},{"answer":"in the middle of the jar","correct":false},{"answer":"at the bottom of the jar","correct":true},{"answer":"mixed throughout the jar","correct":false}],"image":"http://s3-eu-west-1.amazonaws.com/lecturequizuploads/38341e09-b4e2-4354-9bfd-a939658a9552","imageMetadata":{"id":"38341e09-b4e2-4354-9bfd-a939658a9552","resources":""},"resources":"","video":{"id":"","startTime":0,"endTime":0,"service":"youtube","fullUrl":""},"questionFormat":0},{"type":"quiz","question":"Two or more substances that are mixed together but not chemically combined..","time":20000,"points":true,"pointsMultiplier":1,"choices":[{"answer":"mixture","correct":true},{"answer":"pure substances","correct":false},{"answer":"&nbsp;physical changes","correct":false},{"answer":"solid","correct":false}],"image":"http://s3-eu-west-1.amazonaws.com/lecturequizuploads/5cc0ca1e-b09d-4b10-a511-2f655b4261b7_opt","imageMetadata":{"id":"5cc0ca1e-b09d-4b10-a511-2f655b4261b7","resources":""},"resources":"","video":{"id":"","startTime":0,"endTime":0,"service":"youtube","fullUrl":""},"questionFormat":0},{"type":"quiz","question":"A change in a substance that does not change its identity ( a change of state).","time":20000,"points":true,"pointsMultiplier":1,"choices":[{"answer":"melting point","correct":false},{"answer":"matter","correct":false},{"answer":"chemical changes","correct":false},{"answer":"physical changes","correct":true}],"image":"http://s3-eu-west-1.amazonaws.com/lecturequizuploads/fbd812a8-1421-437c-baf0-0fd07c2623a4_opt","imageMetadata":{"id":"fbd812a8-1421-437c-baf0-0fd07c2623a4","resources":""},"resources":"","video":{"id":"","startTime":0,"endTime":0,"service":"youtube","fullUrl":""},"questionFormat":0},{"type":"quiz","question":"A state of matter that has a definite volume and definite shape.","time":20000,"points":true,"pointsMultiplier":1,"choices":[{"answer":"solid","correct":true},{"answer":"liquid","correct":false},{"answer":"gas","correct":false},{"answer":"element","correct":false}],"image":"http://s3-eu-west-1.amazonaws.com/lecturequizuploads/36e3851e-6977-4c5b-8e00-101e95132187_opt","imageMetadata":{"id":"36e3851e-6977-4c5b-8e00-101e95132187","resources":""},"resources":"","video":{"id":"","startTime":0,"endTime":0,"service":"youtube","fullUrl":""},"questionFormat":0},{"type":"quiz","question":"A substance made of only one kind of matter and having definite properties.","time":20000,"points":true,"pointsMultiplier":1,"choices":[{"answer":"pure substances&nbsp;","correct":true},{"answer":"mixtures","correct":false},{"answer":"matter","correct":false},{"answer":"melting point","correct":false}],"image":"http://s3-eu-west-1.amazonaws.com/lecturequizuploads/18c2f9c5-d38e-4dc0-8e30-7e57f6b407a7_opt","imageMetadata":{"id":"18c2f9c5-d38e-4dc0-8e30-7e57f6b407a7","resources":""},"resources":"","video":{"id":"","startTime":0,"endTime":0,"service":"youtube","fullUrl":""},"questionFormat":0},{"type":"quiz","question":"A state of matter that has no definite shape or definite volume.","time":20000,"points":true,"pointsMultiplier":1,"choices":[{"answer":"solid","correct":false},{"answer":"liquid","correct":false},{"answer":"gas","correct":true},{"answer":"element","correct":false}],"image":"http://s3-eu-west-1.amazonaws.com/lecturequizuploads/500ea1a8-ce31-4cc7-ad5e-2f6b890c8ce6_opt","imageMetadata":{"id":"500ea1a8-ce31-4cc7-ad5e-2f6b890c8ce6","resources":""},"resources":"","video":{"id":"","startTime":0,"endTime":0,"service":"youtube","fullUrl":""},"questionFormat":0},{"type":"quiz","question":"A substance that cannot be broken down into other substances by chemical or physical means.","time":20000,"points":true,"pointsMultiplier":1,"choices":[{"answer":"compound&nbsp;","correct":false},{"answer":"mixture","correct":false},{"answer":"element","correct":true},{"answer":"matter","correct":false}],"image":"http://s3-eu-west-1.amazonaws.com/lecturequizuploads/5e4ff6c8-7b10-4f7e-8fe0-9b8cd272e5fe_opt","imageMetadata":{"id":"5e4ff6c8-7b10-4f7e-8fe0-9b8cd272e5fe","resources":""},"resources":"","video":{"id":"","startTime":0,"endTime":0,"service":"youtube","fullUrl":""},"questionFormat":0},{"type":"quiz","question":"Properties of a substance that never change and can be used to identify the substance.","time":20000,"points":true,"pointsMultiplier":1,"choices":[{"answer":"physical changes","correct":false},{"answer":"chemical changes","correct":false},{"answer":"mixtures","correct":false},{"answer":"characteristic properties","correct":true}],"image":"http://s3-eu-west-1.amazonaws.com/lecturequizuploads/de453c1d-283b-4f90-99e8-cde568b172cd_opt","imageMetadata":{"id":"de453c1d-283b-4f90-99e8-cde568b172cd","resources":""},"resources":"","video":{"id":"","startTime":0,"endTime":0,"service":"youtube","fullUrl":""},"questionFormat":0},{"type":"quiz","question":"The temperature at which a substance changes from a liquid to a gas","time":20000,"points":true,"pointsMultiplier":1,"choices":[{"answer":"melting point","correct":false},{"answer":"boiling point","correct":true},{"answer":"chemical changes","correct":false},{"answer":"mixture","correct":false}],"image":"http://s3-eu-west-1.amazonaws.com/lecturequizuploads/78f95dc3-0522-4c72-9e20-a2110c4cf176_opt","imageMetadata":{"id":"78f95dc3-0522-4c72-9e20-a2110c4cf176","resources":""},"resources":"","video":{"id":"","startTime":0,"endTime":0,"service":"youtube","fullUrl":""},"questionFormat":0},{"type":"quiz","question":"A substance made up of two or more elements chemically combined.","time":20000,"points":true,"pointsMultiplier":1,"choices":[{"answer":"element","correct":false},{"answer":"mixture","correct":false},{"answer":"compound","correct":true},{"answer":"matter","correct":false}],"image":"http://s3-eu-west-1.amazonaws.com/lecturequizuploads/c85f900f-d9d3-4f78-ab6c-ec8299163536_opt","imageMetadata":{"id":"c85f900f-d9d3-4f78-ab6c-ec8299163536","resources":""},"resources":"","video":{"id":"","startTime":0,"endTime":0,"service":"youtube","fullUrl":""},"questionFormat":0},{"type":"quiz","question":"A state of matter that has no definite shape but definite volume","time":20000,"points":true,"pointsMultiplier":1,"choices":[{"answer":"solid","correct":false},{"answer":"liquid&nbsp;","correct":true},{"answer":"gas","correct":false},{"answer":"element","correct":false}],"image":"http://s3-eu-west-1.amazonaws.com/lecturequizuploads/b9773f4d-f709-4376-bfb6-44d92bbd4327_opt","imageMetadata":{"id":"b9773f4d-f709-4376-bfb6-44d92bbd4327","resources":""},"resources":"","video":{"id":"","startTime":0,"endTime":0,"service":"youtube","fullUrl":""},"questionFormat":0},{"type":"quiz","question":"A possible explanation for a set of observations or answer to a scientific question is called","time":20000,"points":true,"pointsMultiplier":1,"choices":[{"answer":"prediction","correct":false},{"answer":"hypothesis","correct":true},{"answer":"theory","correct":false},{"answer":"law","correct":false}],"image":"https://media.kahoot.it/059bed05-ebf2-460c-81a6-b2514cf6c331_opt","imageMetadata":{"id":"059bed05-ebf2-460c-81a6-b2514cf6c331","resources":""},"resources":"","video":{"id":"","startTime":0,"endTime":0,"service":"youtube","fullUrl":""},"questionFormat":0},{"type":"quiz","question":"Explaining or interpreting the things you observe based on reasoning is called","time":20000,"points":true,"pointsMultiplier":1,"choices":[{"answer":"observing","correct":false},{"answer":"inferring","correct":true},{"answer":"predicting","correct":false},{"answer":"classifying","correct":false}],"image":"http://s3-eu-west-1.amazonaws.com/lecturequizuploads/c57ea2d7-b1a1-497c-9b67-66b7664dbc6c_opt","imageMetadata":{"id":"c57ea2d7-b1a1-497c-9b67-66b7664dbc6c","resources":""},"resources":"","video":{"id":"","startTime":0,"endTime":0,"service":"youtube","fullUrl":""},"questionFormat":0}],"answerMap":[4,4,4,4,4,4,4,4,4,4,4,4,4,4,4,4,4,4,4,4],"uuid":"fe5fa4a4-dfea-4280-8dc6-6404982bdefe"}